deque_one-0.0.1.dist-info/RECORD
deque_one-0.0.1.dist-info/LICENSE
deque_one-0.0.1.dist-info/WHEEL
deque_one-0.0.1.dist-info/top_level.txt
deque_one-0.0.1.dist-info/METADATA
deque_one/deque.pyi
deque_one/_version.py
deque_one/__init__.py
deque_one/_deque.c
deque_one/deque.cpython-312-darwin.so
