Metadata-Version: 2.1
Name: deque-one
Version: 0.0.1
Summary: like collections.deque, but different
Home-page: https://github.com/styfenschaer/deque-one
Download-URL: https://github.com/styfenschaer/deque-one
Author: Styfen Schär
Author-email: styfen.schaer.blog@gmail.com
Keywords: deque,collections,data-structure,python
Classifier: Development Status :: 3 - Alpha
Classifier: Intended Audience :: Developers
Classifier: License :: OSI Approved :: BSD License
Classifier: Operating System :: OS Independent
Classifier: Programming Language :: Python :: 3.10
Classifier: Programming Language :: Python :: 3.11
Classifier: Programming Language :: Python :: 3.12
License-File: LICENSE
Provides-Extra: dev
Requires-Dist: rich; extra == "dev"
Requires-Dist: numpy; extra == "dev"
